mtANN/__init__.py
mtANN/model.py
mtANN/utils.py
mtANN-1.0.dist-info/METADATA
mtANN-1.0.dist-info/WHEEL
mtANN-1.0.dist-info/top_level.txt
mtANN-1.0.dist-info/RECORD
