Metadata-Version: 2.1
Name: mtANN
Version: 1.0
Summary: Ensemble Multiple References for Single-cell RNA Seuquencing Data Annotation and Unseen Cells Identification
Author: Yi-Xuan Xiong
Author-email: xyxuana@mails.ccnu.edu.cn
Requires-Python: >=3.7
Requires-Dist: pandas
Requires-Dist: numpy
Requires-Dist: scanpy
Requires-Dist: scipy
Requires-Dist: scikit-learn
Requires-Dist: torch
Requires-Dist: giniclust3
Requires-Dist: rpy2
